logicore_django_react_pages/__init__.py
logicore_django_react_pages/views.py
logicore_django_react_pages-1.0.0.dev8.dist-info/LICENSE
logicore_django_react_pages-1.0.0.dev8.dist-info/METADATA
logicore_django_react_pages-1.0.0.dev8.dist-info/WHEEL
logicore_django_react_pages-1.0.0.dev8.dist-info/top_level.txt
logicore_django_react_pages-1.0.0.dev8.dist-info/RECORD
