Metadata-Version: 2.1
Name: logicore-django-react-pages
Version: 1.0.0.dev8
Summary: Post/Redirect/Get-like approach for React + Django AJAX apps
Author-email: Andrei Boltachev <andrewboltachev@gmail.com>
License: Copyright (c) 2012-2022 Scott Chacon and others
Project-URL: Homepage, https://github.com/Logicore-project/logicore-django-react-pages
Project-URL: Bug Tracker, https://github.com/Logicore-project/logicore-django-react-pages/issues
Classifier: Programming Language :: Python :: 3
Classifier: License :: OSI Approved :: MIT License
Classifier: Operating System :: OS Independent
Requires-Python: >=3.7
License-File: LICENSE
Requires-Dist: Django <6
Requires-Dist: logicore-django-react >=1.0.0.dev23
